pandas_connect/__init__.py
pandas_connect/cli.py
pandas_connect/pandas_connect.py
pandas_connect-0.3.2.dist-info/LICENSE
pandas_connect-0.3.2.dist-info/METADATA
pandas_connect-0.3.2.dist-info/WHEEL
pandas_connect-0.3.2.dist-info/entry_points.txt
pandas_connect-0.3.2.dist-info/top_level.txt
pandas_connect-0.3.2.dist-info/RECORD
