Metadata-Version: 2.1
Name: pandas-connect
Version: 0.3.2
Summary: Pandas connection methods for multiple databases. SQL and NoSQL.
Home-page: https://github.com/erichamers/pandas-connect
Author: Eric Hamers
Author-email: erichamers@gmail.com
License: Apache Software License 2.0
Keywords: pandas_connect
Platform: UNKNOWN
Classifier: Development Status :: 2 - Pre-Alpha
Classifier: Intended Audience :: Developers
Classifier: License :: OSI Approved :: Apache Software License
Classifier: Natural Language :: English
Classifier: Programming Language :: Python :: 3
Classifier: Programming Language :: Python :: 3.5
Classifier: Programming Language :: Python :: 3.6
Classifier: Programming Language :: Python :: 3.7
Classifier: Programming Language :: Python :: 3.8
Requires-Python: >=3.5
Requires-Dist: pandas
